{
  "coordenacao": {
    "total": 55,
    "historico": {
      "2025-06-30": 4,
      "2025-07-01": 14,
      "2025-07-02": 19,
      "2025-07-03": 2,
      "2025-07-08": 10,
      "2025-07-10": 6
    }
  },
  "tarifas-complementares": {
    "total": 28,
    "historico": {
      "2025-06-30": 1,
      "2025-07-02": 22,
      "2025-07-03": 3,
      "2025-07-08": 2
    }
  },
  "agendamento": {
    "total": 180,
    "historico": {
      "2025-06-30": 13,
      "2025-07-01": 29,
      "2025-07-02": 96,
      "2025-07-03": 1,
      "2025-07-08": 33,
      "2025-07-10": 8
    }
  },
  "telas-informa": {
    "total": 18,
    "historico": {
      "2025-07-01": 1,
      "2025-07-02": 13,
      "2025-07-03": 2,
      "2025-07-08": 1,
      "2025-07-10": 1
    }
  },
  "Raia": {
    "total": 6,
    "historico": {
      "2025-07-02": 6
    }
  },
  "Profarma": {
    "total": 9,
    "historico": {
      "2025-07-02": 5,
      "2025-07-03": 1,
      "2025-07-08": 3
    }
  },
  "GSK": {
    "total": 3,
    "historico": {
      "2025-07-02": 3
    }
  },
  "RAIA": {
    "total": 2,
    "historico": {
      "2025-07-02": 2
    }
  },
  "teste": {
    "total": 19,
    "historico": {
      "2025-07-02": 16,
      "2025-07-03": 3
    }
  },
  "aereo": {
    "total": 2,
    "historico": {
      "2025-07-03": 2
    }
  },
  "raia": {
    "total": 1,
    "historico": {
      "2025-07-08": 1
    }
  },
  "recebimento-intec": {
    "total": 5,
    "historico": {
      "2025-07-08": 2,
      "2025-07-10": 3
    }
  }
}